{"results": [{"headline": "Sleepers (Movie)  ", "publication_date": "1996-10-18", "byline": "Janet Maslin", "critics_pick": 0, "date_updated": "2016-03-30 06:49:44", "opening_date": "1996-10-18", "display_title": "Sleepers", "link": {"url": "http://www.nytimes.com/movie/review?res=9502E6DF1331F93BA25753C1A960958260", "suggested_link_text": "Read the New York Times Review of Sleepers", "type": "article"}, "mpaa_rating": "R", "summary_short": "Assistant D.A. and reporter conspire to fix friends' trial. Phony Hell's Kitchen baloney.", "multimedia": null}, {"headline": "Jude (Movie)  ", "publication_date": "1996-10-18", "byline": "Lawrence Van Gelder", "critics_pick": 0, "date_updated": "2016-03-30 07:12:14", "opening_date": "1996-10-18", "display_title": "Jude", "link": {"url": "http://www.nytimes.com/movie/review?res=9A04E1DF1331F93BA25753C1A960958260", "suggested_link_text": "Read the New York Times Review of Jude", "type": "article"}, "mpaa_rating": "R", "summary_short": "Hardy's young hero challenges social conventions. Handsome but gravely flawed.", "multimedia": null}, {"headline": "Freeway (Movie)  ", "publication_date": "1996-10-18", "byline": "Lawrence Van Gelder", "critics_pick": 0, "date_updated": "2016-03-30 06:48:47", "opening_date": null, "display_title": "Freeway", "link": {"url": "http://www.nytimes.com/movie/review?res=9F0DE1DF1331F93BA25753C1A960958260", "suggested_link_text": "Read the New York Times Review of Freeway", "type": "article"}, "mpaa_rating": "R", "summary_short": "Teenage runaway and serial killer. Distasteful ``Red Riding Hood'' update.", "multimedia": null}, {"headline": "Ed's Next Move (Movie)  ", "publication_date": "1996-10-18", "byline": "Janet Maslin", "critics_pick": 0, "date_updated": "2016-03-30 06:53:50", "opening_date": "1996-09-27", "display_title": "Ed's Next Move", "link": {"url": "http://www.nytimes.com/movie/review?res=9506E1DE1331F93BA25753C1A960958260", "suggested_link_text": "Read the New York Times Review of Ed's Next Move", "type": "article"}, "mpaa_rating": "R", "summary_short": "Wisconsinite in New York loves folk singer. Amusing but thin.", "multimedia": null}, {"headline": "Get on the Bus (Movie)  ", "publication_date": "1996-10-16", "byline": "Janet Maslin", "critics_pick": 0, "date_updated": "2016-03-30 07:26:57", "opening_date": "1996-10-16", "display_title": "Get on the Bus", "link": {"url": "http://www.nytimes.com/movie/review?res=9502E4D61731F935A25753C1A960958260", "suggested_link_text": "Read the New York Times Review of Get on the Bus", "type": "article"}, "mpaa_rating": "R", "summary_short": "Million Man March, via Spike Lee. Small but earnest.", "multimedia": null}, {"headline": "Niki de Saint Phalle (Movie)  ", "publication_date": "1996-10-16", "byline": "Lawrence Van Gelder", "critics_pick": 0, "date_updated": "2016-03-30 06:43:10", "opening_date": "1996-10-16", "display_title": "Who Is the Monster...You or Me?", "link": {"url": "http://www.nytimes.com/movie/review?res=9905E5DD1431F935A25753C1A960958260", "suggested_link_text": "Read the New York Times Review of Who Is the Monster...You or Me?", "type": "article"}, "mpaa_rating": "", "summary_short": "", "multimedia": null}, {"headline": "People Vs Larry Flynt, the (Movie)  ", "publication_date": "1996-10-12", "byline": "Janet Maslin", "critics_pick": 1, "date_updated": "2016-03-30 06:52:04", "opening_date": "1997-01-10", "display_title": "The People vs. Larry Flynt", "link": {"url": "http://www.nytimes.com/movie/review?res=9400E6D8103EF931A25753C1A960958260", "suggested_link_text": "Read the New York Times Review of The People vs. Larry Flynt", "type": "article"}, "mpaa_rating": "R", "summary_short": "Hustler magazine publisher's First Amendment battle. Perfectly serious and shamelessly entertaining.", "multimedia": null}, {"headline": "Underground (Movie)  ", "publication_date": "1996-10-12", "byline": "Janet Maslin", "critics_pick": 1, "date_updated": "2016-03-30 06:58:16", "opening_date": "1997-06-20", "display_title": "Underground", "link": {"url": "http://www.nytimes.com/movie/review?res=9C01E7DA103EF931A25753C1A960958260", "suggested_link_text": "Read the New York Times Review of Underground", "type": "article"}, "mpaa_rating": "Not Rated", "summary_short": "A man tricks his friend and comrades in 1941 Yugoslavia, leaving them hidden in a cellar years after the war has ended. Wild, sprawling allegory.", "multimedia": null}, {"headline": "Rolling Stones Rock-and-Roll Circus, the (Movie)  ", "publication_date": "1996-10-12", "byline": "Janet Maslin", "critics_pick": 0, "date_updated": "2016-03-30 07:25:29", "opening_date": null, "display_title": "The Rolling Stones Rock and Roll Circus", "link": {"url": "http://www.nytimes.com/movie/review?res=9D02E1DB103EF931A25753C1A960958260", "suggested_link_text": "Read the New York Times Review of The Rolling Stones Rock and Roll Circus", "type": "article"}, "mpaa_rating": "", "summary_short": "", "multimedia": null}, {"headline": "Mandela (Movie)  ", "publication_date": "1996-10-12", "byline": "Stephen Holden", "critics_pick": 0, "date_updated": "2016-03-30 06:41:39", "opening_date": "1997-03-21", "display_title": "Mandela", "link": {"url": "http://www.nytimes.com/movie/review?res=9902E5D9103EF931A25753C1A960958260", "suggested_link_text": "Read the New York Times Review of Mandela", "type": "article"}, "mpaa_rating": "", "summary_short": "", "multimedia": null}, {"headline": "Suburbia (Movie)", "publication_date": "1996-10-11", "byline": "Janet Maslin", "critics_pick": 0, "date_updated": "2016-03-30 06:42:14", "opening_date": "1997-02-07", "display_title": "Suburbia", "link": {"url": "http://www.nytimes.com/movie/review?res=9C0DE2D8123EF932A25753C1A960958260", "suggested_link_text": "Read the New York Times Review of Suburbia", "type": "article"}, "mpaa_rating": "R", "summary_short": "High school geek turned rock star. Stinging.", "multimedia": null}, {"headline": "Trees Lounge (Movie)  ", "publication_date": "1996-10-11", "byline": "Stephen Holden", "critics_pick": 0, "date_updated": "2016-03-30 07:15:32", "opening_date": "1996-10-11", "display_title": "Trees Lounge", "link": {"url": "http://www.nytimes.com/movie/review?res=980DE2D9123EF932A25753C1A960958260", "suggested_link_text": "Read the New York Times Review of Trees Lounge", "type": "article"}, "mpaa_rating": "R", "summary_short": "Unemployed mechanic's downward spiral. Sketchy but wrenching.", "multimedia": null}, {"headline": "Michael Collins (Movie)  ", "publication_date": "1996-10-11", "byline": "Janet Maslin", "critics_pick": 0, "date_updated": "2016-03-30 06:48:09", "opening_date": "1996-10-25", "display_title": "Michael Collins", "link": {"url": "http://www.nytimes.com/movie/review?res=9C01EED9123EF932A25753C1A960958260", "suggested_link_text": "Read the New York Times Review of Michael Collins", "type": "article"}, "mpaa_rating": "R", "summary_short": "Irish freedom fighter and statesman. Sugarcoated but passionate drama.", "multimedia": null}, {"headline": "Love Is All There Is (Movie)  ", "publication_date": "1996-10-11", "byline": "Lawrence Van Gelder", "critics_pick": 0, "date_updated": "2016-03-30 06:49:33", "opening_date": "1996-05-10", "display_title": "Love Is All There Is", "link": {"url": "http://www.nytimes.com/movie/review?res=9C07E0D9123EF932A25753C1A960958260", "suggested_link_text": "Read the New York Times Review of Love Is All There Is", "type": "article"}, "mpaa_rating": "R", "summary_short": "''Romeo and Juliet'' with feuding restaurateur families. Savory comedy.", "multimedia": null}, {"headline": "Long Kiss Goodnight, The (Movie)  ", "publication_date": "1996-10-11", "byline": "JANET MASLIN", "critics_pick": 0, "date_updated": "2016-03-30 07:16:45", "opening_date": "1996-10-11", "display_title": "The Long Kiss Goodnight", "link": {"url": "http://www.nytimes.com/movie/review?res=9D06E5D9123EF932A25753C1A960958260", "suggested_link_text": "Read the New York Times Review of The Long Kiss Goodnight", "type": "article"}, "mpaa_rating": "R", "summary_short": "Amnesiac New England mom remembers past as government assassin. Sharp and mean-spirited.", "multimedia": null}, {"headline": "Lilies (Movie)  ", "publication_date": "1996-10-11", "byline": "Stephen Holden", "critics_pick": 0, "date_updated": "2016-03-30 07:06:04", "opening_date": null, "display_title": "Lilies", "link": {"url": "http://www.nytimes.com/movie/review?res=9F03EED8123EF932A25753C1A960958260", "suggested_link_text": "Read the New York Times Review of Lilies", "type": "article"}, "mpaa_rating": "R", "summary_short": "", "multimedia": null}, {"headline": "L5. First City in Space (Movie)  ", "publication_date": "1996-10-11", "byline": "Stephen Holden", "critics_pick": 0, "date_updated": "2016-03-30 07:30:29", "opening_date": "1996-10-11", "display_title": "L5: First City In Space", "link": {"url": "http://www.nytimes.com/movie/review?res=9B04EEDC123EF932A25753C1A960958260", "suggested_link_text": "Read the New York Times Review of L5: First City In Space", "type": "article"}, "mpaa_rating": "", "summary_short": "", "multimedia": null}, {"headline": "Ghost and the Darkness, The (Movie)  ", "publication_date": "1996-10-11", "byline": "JANET MASLIN", "critics_pick": 0, "date_updated": "2016-03-30 07:22:00", "opening_date": "1996-10-11", "display_title": "The Ghost and the Darkness", "link": {"url": "http://www.nytimes.com/movie/review?res=9F05E0D9123EF932A25753C1A960958260", "suggested_link_text": "Read the New York Times Review of The Ghost and the Darkness", "type": "article"}, "mpaa_rating": "R", "summary_short": "Two guys, two lions and a trans-Africa railway. ``Jaws'' with paws.", "multimedia": null}, {"headline": "Chamber, The (Movie)  ", "publication_date": "1996-10-11", "byline": "JANET MASLIN", "critics_pick": 0, "date_updated": "2016-03-30 07:06:03", "opening_date": "1996-10-11", "display_title": "The Chamber", "link": {"url": "http://www.nytimes.com/movie/review?res=9F02E1D9123EF932A25753C1A960958260", "suggested_link_text": "Read the New York Times Review of The Chamber", "type": "article"}, "mpaa_rating": "R", "summary_short": "Klansman on death row, via Grisham. Superlative Hackman, otherwise not believable.", "multimedia": null}, {"headline": "Grass Harp, the (Movie)  ", "publication_date": "1996-10-11", "byline": "LAWRENCE VAN GELDER", "critics_pick": 0, "date_updated": "2016-03-30 06:42:33", "opening_date": "1996-10-11", "display_title": "The Grass Harp", "link": {"url": "http://www.nytimes.com/movie/review?res=9502EFDC123EF932A25753C1A960958260", "suggested_link_text": "Read the New York Times Review of The Grass Harp", "type": "article"}, "mpaa_rating": "PG", "summary_short": "Capote's Depression-era orphan and Southern spinster cousins. Poignant.", "multimedia": null}], "num_results": 20, "status": "OK", "copyright": "Copyright (c) 2017 The New York Times Company. All Rights Reserved.", "has_more": true}