{"results": [{"headline": "Silhouettes (Movie)", "publication_date": "1982-04-26", "byline": "JOHN CORRY", "critics_pick": 0, "date_updated": "2016-03-30 06:52:05", "opening_date": null, "display_title": "Silhouettes", "link": {"url": "http://www.nytimes.com/movie/review?res=9400E3DB103BF935A15757C0A964948260", "suggested_link_text": "Read the New York Times Review of Silhouettes", "type": "article"}, "mpaa_rating": "", "summary_short": "", "multimedia": null}, {"headline": "Dance Craze (Movie)", "publication_date": "1982-04-25", "byline": "Janet Maslin", "critics_pick": 0, "date_updated": "2016-03-30 07:29:13", "opening_date": null, "display_title": "Dance Craze", "link": {"url": "http://www.nytimes.com/movie/review?res=9E0CE7D71038F936A15757C0A964948260", "suggested_link_text": "Read the New York Times Review of Dance Craze", "type": "article"}, "mpaa_rating": "", "summary_short": "", "multimedia": null}, {"headline": "Malou (Movie)", "publication_date": "1982-04-25", "byline": "VINCENT CANBY", "critics_pick": 0, "date_updated": "2016-03-30 07:23:27", "opening_date": null, "display_title": "Malou", "link": {"url": "http://www.nytimes.com/movie/review?res=9503E1D8123BF936A15757C0A964948260", "suggested_link_text": "Read the New York Times Review of Malou", "type": "article"}, "mpaa_rating": "R", "summary_short": "", "multimedia": null}, {"headline": "I Love You (Movie)", "publication_date": "1982-04-25", "byline": "JANET MASLIN", "critics_pick": 0, "date_updated": "2016-03-30 06:55:52", "opening_date": null, "display_title": "I Love You", "link": {"url": "http://www.nytimes.com/movie/review?res=9D03E7DA143BF936A15757C0A964948260", "suggested_link_text": "Read the New York Times Review of I Love You", "type": "article"}, "mpaa_rating": "", "summary_short": "", "multimedia": null}, {"headline": "CHAN IS MISSING (MOVIE)", "publication_date": "1982-04-24", "byline": "Vincent Canby", "critics_pick": 1, "date_updated": "2016-03-30 07:25:16", "opening_date": "1982-06-04", "display_title": "Chan Is Missing", "link": {"url": "http://www.nytimes.com/movie/review?res=EE05E7DF173CE760BC4C51DFB2668389699EDE", "suggested_link_text": "Read the New York Times Review of Chan Is Missing", "type": "article"}, "mpaa_rating": "", "summary_short": "Two San Francisco cabbies after thief.", "multimedia": null}, {"headline": "If You Could See What I Hear (Movie)", "publication_date": "1982-04-23", "byline": "Janet Maslin", "critics_pick": 0, "date_updated": "2016-03-30 07:22:10", "opening_date": "1982-04-23", "display_title": "If You Could See What I Hear", "link": {"url": "http://www.nytimes.com/movie/review?res=9C02E7DA143BF930A15757C0A964948260", "suggested_link_text": "Read the New York Times Review of If You Could See What I Hear", "type": "article"}, "mpaa_rating": "PG", "summary_short": "Blind singer-composer's college days. Well done but pat.", "multimedia": null}, {"headline": "Unfinished Piece for Player Piano, An (Movie)", "publication_date": "1982-04-23", "byline": "Janet Maslin", "critics_pick": 0, "date_updated": "2016-03-30 07:19:38", "opening_date": null, "display_title": "An Unfinished Piece for Player Piano", "link": {"url": "http://www.nytimes.com/movie/review?res=9F0CE4DB103BF930A15757C0A964948260", "suggested_link_text": "Read the New York Times Review of An Unfinished Piece for Player Piano", "type": "article"}, "mpaa_rating": "", "summary_short": "Impoverished Russian aristocrat's party, circa 1910, via Chekhov play.", "multimedia": null}, {"headline": "Marianne and Juliane (Movie)", "publication_date": "1982-04-22", "byline": "JANET MASLIN", "critics_pick": 0, "date_updated": "2016-03-30 07:28:17", "opening_date": null, "display_title": "Marianne and Julianne", "link": {"url": "http://www.nytimes.com/movie/review?res=9C00E1D8123BF931A15757C0A964948260", "suggested_link_text": "Read the New York Times Review of Marianne and Julianne", "type": "article"}, "mpaa_rating": "", "summary_short": "", "multimedia": null}, {"headline": "My Son, My Precious (Movie)", "publication_date": "1982-04-21", "byline": "JANET MASLIN", "critics_pick": 0, "date_updated": "2016-03-30 07:05:11", "opening_date": null, "display_title": "My Son, My Precious ", "link": {"url": "http://www.nytimes.com/movie/review?res=9E01E1D8123BF932A15757C0A964948260", "suggested_link_text": "Read the New York Times Review of My Son, My Precious ", "type": "article"}, "mpaa_rating": "", "summary_short": "", "multimedia": null}, {"headline": "Budapest Tales (Movie)", "publication_date": "1982-04-21", "byline": "HERBERT MITGANG", "critics_pick": 0, "date_updated": "2016-03-30 07:09:14", "opening_date": "1985-10-02", "display_title": "Budapesti Mesek", "link": {"url": "http://www.nytimes.com/movie/review?res=9403E7D71038F932A15757C0A964948260", "suggested_link_text": "Read the New York Times Review of Budapesti Mesek", "type": "article"}, "mpaa_rating": "", "summary_short": "", "multimedia": null}, {"headline": "Who Shall Live and Who Shall Die (Movie)", "publication_date": "1982-04-19", "byline": "VINCENT CANBY", "critics_pick": 0, "date_updated": "2016-03-30 06:42:58", "opening_date": null, "display_title": "Who Shall Live and Who Shall Die?", "link": {"url": "http://www.nytimes.com/movie/review?res=9503E4DB103BF93AA25757C0A964948260", "suggested_link_text": "Read the New York Times Review of Who Shall Live and Who Shall Die?", "type": "article"}, "mpaa_rating": "", "summary_short": "", "multimedia": null}, {"headline": "They Don't Wear Black Tie (Movie)", "publication_date": "1982-04-18", "byline": "Janet Maslin", "critics_pick": 0, "date_updated": "2016-03-30 07:30:36", "opening_date": null, "display_title": "Eles n\u00c3\u00a3o usam black-tie", "link": {"url": "http://www.nytimes.com/movie/review?res=9C00E4DB103BF93BA25757C0A964948260", "suggested_link_text": "Read the New York Times Review of Eles n\u00c3\u00a3o usam black-tie", "type": "article"}, "mpaa_rating": "", "summary_short": "", "multimedia": null}, {"headline": "Mater Amatisima (Movie)", "publication_date": "1982-04-18", "byline": "VINCENT CANBY", "critics_pick": 0, "date_updated": "2016-03-30 06:45:40", "opening_date": null, "display_title": "Mater Amatisima", "link": {"url": "http://www.nytimes.com/movie/review?res=9404E1D8123BF93BA25757C0A964948260", "suggested_link_text": "Read the New York Times Review of Mater Amatisima", "type": "article"}, "mpaa_rating": "", "summary_short": "", "multimedia": null}, {"headline": "Amateur, The (Movie)", "publication_date": "1982-04-17", "byline": "JANET MASLIN", "critics_pick": 0, "date_updated": "2016-03-30 06:57:15", "opening_date": "1982-02-12", "display_title": "The Amateur", "link": {"url": "http://www.nytimes.com/movie/review?res=9C00E7D71038F934A25757C0A964948260", "suggested_link_text": "Read the New York Times Review of The Amateur", "type": "article"}, "mpaa_rating": "R", "summary_short": "C.I.A. man avenges murder. Standard.", "multimedia": null}, {"headline": "SMASH PALACE (MOVIE)", "publication_date": "1982-04-16", "byline": "Janet Maslin", "critics_pick": 1, "date_updated": "2016-03-30 07:12:48", "opening_date": "1982-04-30", "display_title": "Smash Palace", "link": {"url": "http://www.nytimes.com/movie/review?res=EE05E7DF173BE070BC4E52DFB2668389699EDE", "suggested_link_text": "Read the New York Times Review of Smash Palace", "type": "article"}, "mpaa_rating": "", "summary_short": "Compelling, well played drama of marital tensions, from New Zealand.", "multimedia": null}, {"headline": "DIVA (MOVIE)", "publication_date": "1982-04-16", "byline": "Vincent Canby", "critics_pick": 1, "date_updated": "2016-03-30 06:45:44", "opening_date": "1982-04-23", "display_title": "Diva", "link": {"url": "http://www.nytimes.com/movie/review?res=9503E6DA143BF935A25757C0A964948260", "suggested_link_text": "Read the New York Times Review of Diva", "type": "article"}, "mpaa_rating": "R", "summary_short": "Stylish, tantalizing French suspense-puzzle, and quite gory. But hang on.", "multimedia": null}, {"headline": "Wrong is Right (Movie)", "publication_date": "1982-04-16", "byline": "VINCENT CANBY", "critics_pick": 0, "date_updated": "2016-03-30 07:10:32", "opening_date": "1982-05-14", "display_title": "Wrong Is Right", "link": {"url": "http://www.nytimes.com/movie/review?res=9A0CE5DB103BF935A25757C0A964948260", "suggested_link_text": "Read the New York Times Review of Wrong Is Right", "type": "article"}, "mpaa_rating": "R", "summary_short": "Deadpan mulligan-stew adventure.", "multimedia": null}, {"headline": "Garde a Vue (Movie)", "publication_date": "1982-04-16", "byline": "Janet Maslin", "critics_pick": 0, "date_updated": "2016-03-30 06:44:59", "opening_date": null, "display_title": "Garde a Vue", "link": {"url": "http://www.nytimes.com/movie/review?res=9B02E6DA143BF935A25757C0A964948260", "suggested_link_text": "Read the New York Times Review of Garde a Vue", "type": "article"}, "mpaa_rating": "", "summary_short": "", "multimedia": null}, {"headline": "Ticket of No Return (Movie)", "publication_date": "1982-04-14", "byline": "JANET MASLIN", "critics_pick": 0, "date_updated": "2016-03-30 06:42:14", "opening_date": null, "display_title": "Bildnis einer Trinkerin", "link": {"url": "http://www.nytimes.com/movie/review?res=9C02E5DB103BF937A25757C0A964948260", "suggested_link_text": "Read the New York Times Review of Bildnis einer Trinkerin", "type": "article"}, "mpaa_rating": "", "summary_short": "", "multimedia": null}, {"headline": "Era Notte a Roma (Movie)", "publication_date": "1982-04-09", "byline": "VINCENT CANBY", "critics_pick": 0, "date_updated": "2016-03-30 06:50:32", "opening_date": null, "display_title": "It Was Night in Rome", "link": {"url": "http://www.nytimes.com/movie/review?res=9F0CE6DA143BF93AA35757C0A964948260", "suggested_link_text": "Read the New York Times Review of It Was Night in Rome", "type": "article"}, "mpaa_rating": "", "summary_short": "", "multimedia": null}], "num_results": 20, "status": "OK", "copyright": "Copyright (c) 2017 The New York Times Company. All Rights Reserved.", "has_more": true}