{"results": [{"headline": "First Time, The (Movie)  ", "publication_date": "1998-03-31", "byline": "JANET MASLIN", "critics_pick": 0, "date_updated": "2016-03-30 06:47:31", "opening_date": null, "display_title": "The First Time", "link": {"url": "http://www.nytimes.com/movie/review?res=9505E6DC103BF932A05750C0A96E958260", "suggested_link_text": "Read the New York Times Review of The First Time", "type": "article"}, "mpaa_rating": "", "summary_short": "", "multimedia": null}, {"headline": "See the Sea (Movie)  ", "publication_date": "1998-03-31", "byline": "Janet Maslin", "critics_pick": 0, "date_updated": "2016-03-30 06:57:53", "opening_date": "1998-08-28", "display_title": "See the Sea", "link": {"url": "http://www.nytimes.com/movie/review?res=9400E5DB103AF932A05750C0A96E958260", "suggested_link_text": "Read the New York Times Review of See the Sea", "type": "article"}, "mpaa_rating": "Not Rated", "summary_short": "Englishwoman with infant invites hitchhiker into isolated island cottage. Expertly chilling.", "multimedia": null}, {"headline": "Barney's Great Adventure (Movie)  ", "publication_date": "1998-03-29", "byline": "Patricia S. McCormick", "critics_pick": 0, "date_updated": "2016-03-30 07:28:38", "opening_date": "1998-04-03", "display_title": "Barney's Great Adventure", "link": {"url": "http://www.nytimes.com/movie/review?res=9905E2DC163BF93AA15750C0A96E958260", "suggested_link_text": "Read the New York Times Review of Barney's Great Adventure", "type": "article"}, "mpaa_rating": "G", "summary_short": "Talking purple dinosaur leads children on egg hunt.", "multimedia": null}, {"headline": "Leila (Movie)  ", "publication_date": "1998-03-28", "byline": "Stephen Holden", "critics_pick": 1, "date_updated": "2016-03-30 06:51:28", "opening_date": null, "display_title": "Leila", "link": {"url": "http://www.nytimes.com/movie/review?res=9D02EFDB143BF93BA15750C0A96E958260", "suggested_link_text": "Read the New York Times Review of Leila", "type": "article"}, "mpaa_rating": "", "summary_short": "The calculating monster who pulls the strings in Dariush Mehrjui's heartbreaking film is an imperious mother-in-law (Jamileh Sheikhi) whose selfishness and pride put her in the same elite league with some of Hollywood's most formidable Gorgons. On learning that her daughter-in-law is infertile, this termagant, who is obsessed with having a male grandchild to carry on the family line, systematically undermines the marriage of her only son, Reza (Ali Mosaffa). Without being simplistic, the gripping and beautifully acted film suggests that in Iran, contemporary attitudes toward love and marriage and modern psychology are no match for the combined force of social pressure and Islamic tradition when ruthlessly appropriated as weapons of intimidation. &quot;Leila&quot; is, in a word, devastating. - Stephen Holden", "multimedia": null}, {"headline": "Goshogaoka (Movie)  ", "publication_date": "1998-03-28", "byline": "Stephen Holden", "critics_pick": 0, "date_updated": "2016-03-30 07:15:38", "opening_date": "1998-03-28", "display_title": "Goshogaoka", "link": {"url": "http://www.nytimes.com/movie/review?res=9D0DE7DB143BF93BA15750C0A96E958260", "suggested_link_text": "Read the New York Times Review of Goshogaoka", "type": "article"}, "mpaa_rating": "", "summary_short": "", "multimedia": null}, {"headline": "Under the Skin (Movie)  ", "publication_date": "1998-03-28", "byline": "Janet Maslin", "critics_pick": 0, "date_updated": "2016-03-30 07:14:08", "opening_date": "1998-05-22", "display_title": "Under the Skin", "link": {"url": "http://www.nytimes.com/movie/review?res=9504E5DB143BF93BA15750C0A96E958260", "suggested_link_text": "Read the New York Times Review of Under the Skin", "type": "article"}, "mpaa_rating": "", "summary_short": "A young woman embarks upon a sexual odyssey in reaction to her mother's sudden death from a brain tumor. Splendidly acted coming-of-age story.", "multimedia": null}, {"headline": "Ride (Movie)  ", "publication_date": "1998-03-28", "byline": "Lawrence Van Gelder", "critics_pick": 0, "date_updated": "2016-03-30 07:30:18", "opening_date": "1998-03-27", "display_title": "Ride", "link": {"url": "http://www.nytimes.com/movie/review?res=9403E3DC143BF93BA15750C0A96E958260", "suggested_link_text": "Read the New York Times Review of Ride", "type": "article"}, "mpaa_rating": "R", "summary_short": "Busload of rappers and friends traveling to Miami. It's a long way from Harlem, especially in this ramshackle vehicle.", "multimedia": null}, {"headline": "Cosmos (Movie)  ", "publication_date": "1998-03-28", "byline": "ANITA GATES", "critics_pick": 0, "date_updated": "2016-03-30 07:27:39", "opening_date": null, "display_title": "Cosmos", "link": {"url": "http://www.nytimes.com/movie/review?res=9C0CE1DA143BF93BA15750C0A96E958260", "suggested_link_text": "Read the New York Times Review of Cosmos", "type": "article"}, "mpaa_rating": "", "summary_short": "", "multimedia": null}, {"headline": "Lucky Star, The (Movie)  ", "publication_date": "1998-03-28", "byline": "STEPHEN HOLDEN", "critics_pick": 0, "date_updated": "2016-03-30 06:46:53", "opening_date": null, "display_title": "The Lucky Star", "link": {"url": "http://www.nytimes.com/movie/review?res=9B07E5DB143BF93BA15750C0A96E958260", "suggested_link_text": "Read the New York Times Review of The Lucky Star", "type": "article"}, "mpaa_rating": "", "summary_short": "", "multimedia": null}, {"headline": "Newton Boys, The (Movie)  ", "publication_date": "1998-03-27", "byline": "Janet Maslin", "critics_pick": 0, "date_updated": "2016-03-30 07:30:00", "opening_date": "1998-03-27", "display_title": "The Newton Boys", "link": {"url": "http://www.nytimes.com/movie/review?res=9C02EED9163BF934A15750C0A96E958260", "suggested_link_text": "Read the New York Times Review of The Newton Boys", "type": "article"}, "mpaa_rating": "PG-13", "summary_short": "Texas farmer brothers become bank robbers. Old hat.", "multimedia": null}, {"headline": "Meet the Deedles (Movie)  ", "publication_date": "1998-03-27", "byline": "Anita Gates", "critics_pick": 0, "date_updated": "2016-03-30 07:13:52", "opening_date": "1998-03-27", "display_title": "Meet the Deedles", "link": {"url": "http://www.nytimes.com/movie/review?res=9E02E3D7173BF934A15750C0A96E958260", "suggested_link_text": "Read the New York Times Review of Meet the Deedles", "type": "article"}, "mpaa_rating": "PG", "summary_short": "Surfer twins mistaken for forest-ranger recruits. Juvenile.", "multimedia": null}, {"headline": "Smoke Signals (Movie)  ", "publication_date": "1998-03-27", "byline": "Janet Maslin", "critics_pick": 0, "date_updated": "2016-03-30 07:10:40", "opening_date": "1998-06-26", "display_title": "Smoke Signals", "link": {"url": "http://www.nytimes.com/movie/review?res=9C07E2D9163BF934A15750C0A96E958260", "suggested_link_text": "Read the New York Times Review of Smoke Signals", "type": "article"}, "mpaa_rating": "", "summary_short": "American Indian buddies on the road. Inventive, affectionate and witty.", "multimedia": null}, {"headline": "Proposition, The (Movie)  ", "publication_date": "1998-03-27", "byline": "Stephen Holden", "critics_pick": 0, "date_updated": "2016-03-30 06:46:21", "opening_date": "1998-03-27", "display_title": "The Proposition", "link": {"url": "http://www.nytimes.com/movie/review?res=9C0DE3DB163BF934A15750C0A96E958260", "suggested_link_text": "Read the New York Times Review of The Proposition", "type": "article"}, "mpaa_rating": "R", "summary_short": "Surrogate fatherhood in 1930's Boston. Overplotted and sudsy.", "multimedia": null}, {"headline": "No Looking Back (Movie)  ", "publication_date": "1998-03-27", "byline": "Stephen Holden", "critics_pick": 0, "date_updated": "2016-03-30 07:13:03", "opening_date": "1998-03-27", "display_title": "No Looking Back", "link": {"url": "http://www.nytimes.com/movie/review?res=950DEED9163BF934A15750C0A96E958260", "suggested_link_text": "Read the New York Times Review of No Looking Back", "type": "article"}, "mpaa_rating": "R", "summary_short": "Penniless man tries to win back hometown girlfriend.  Actors too glamorous for their own good.", "multimedia": null}, {"headline": "Character (Movie)  ", "publication_date": "1998-03-27", "byline": "Janet Maslin", "critics_pick": 0, "date_updated": "2016-03-30 07:18:04", "opening_date": "1998-03-27", "display_title": "Character", "link": {"url": "http://www.nytimes.com/movie/review?res=9B00EFD9163BF934A15750C0A96E958260", "suggested_link_text": "Read the New York Times Review of Character", "type": "article"}, "mpaa_rating": "R", "summary_short": "In Rotterdam, rich man's illegitimate son driven to murder. Best foreign film Oscar. Abruptly powerful.", "multimedia": null}, {"headline": "Genealogies of A Crime (Movie)  ", "publication_date": "1998-03-27", "byline": "Stephen Holden", "critics_pick": 0, "date_updated": "2016-03-30 06:50:57", "opening_date": "1998-03-27", "display_title": "Genealogies d'un crime", "link": {"url": "http://www.nytimes.com/movie/review?res=9902E7D9163BF934A15750C0A96E958260", "suggested_link_text": "Read the New York Times Review of Genealogies d'un crime", "type": "article"}, "mpaa_rating": "", "summary_short": "Lawyer imagines herself the murder victim of the young man she is defending. Delightful metaphysical comedy.", "multimedia": null}, {"headline": "Frozen (Movie)  ", "publication_date": "1998-03-25", "byline": "Anita Gates", "critics_pick": 0, "date_updated": "2016-03-30 07:27:57", "opening_date": "1997-00-00", "display_title": "Frozen", "link": {"url": "http://www.nytimes.com/movie/review?res=9504E6DF1138F936A15750C0A96E958260", "suggested_link_text": "Read the New York Times Review of Frozen", "type": "article"}, "mpaa_rating": "", "summary_short": "", "multimedia": null}, {"headline": "Price Above Rubies, A (Movie)  ", "publication_date": "1998-03-25", "byline": "Janet Maslin", "critics_pick": 0, "date_updated": "2016-03-30 06:55:40", "opening_date": "1998-03-25", "display_title": "A Price Above Rubies", "link": {"url": "http://www.nytimes.com/movie/review?res=9B07E6DF1138F936A15750C0A96E958260", "suggested_link_text": "Read the New York Times Review of A Price Above Rubies", "type": "article"}, "mpaa_rating": "R", "summary_short": "Orthodox Jew challenges religious traditions with husband and family. Lively and engrossing.", "multimedia": null}, {"headline": "James Ellroy: Demon Dog of American Crime Fiction (Movie)  ", "publication_date": "1998-03-25", "byline": "JANET MASLIN", "critics_pick": 0, "date_updated": "2016-03-30 06:50:16", "opening_date": "1998-03-25", "display_title": "James Ellroy: Demon Dog of American Crime Fiction", "link": {"url": "http://www.nytimes.com/movie/review?res=9501E2DE1138F936A15750C0A96E958260", "suggested_link_text": "Read the New York Times Review of James Ellroy: Demon Dog of American Crime Fiction", "type": "article"}, "mpaa_rating": "", "summary_short": "", "multimedia": null}, {"headline": "Wild Things (Movie)  ", "publication_date": "1998-03-20", "byline": "Janet Maslin", "critics_pick": 0, "date_updated": "2016-03-30 07:12:50", "opening_date": "1998-03-20", "display_title": "Wild Things", "link": {"url": "http://www.nytimes.com/movie/review?res=9C00E0D91F39F933A15750C0A96E958260", "suggested_link_text": "Read the New York Times Review of Wild Things", "type": "article"}, "mpaa_rating": "Not Rated", "summary_short": "Florida cop investigates rape charges. Slick and steamy.", "multimedia": null}], "num_results": 20, "status": "OK", "copyright": "Copyright (c) 2017 The New York Times Company. All Rights Reserved.", "has_more": true}