{"results": [{"headline": "SEPTEMBER (MOVIE)", "publication_date": "1987-12-18", "byline": "Vincent Canby", "critics_pick": 0, "date_updated": "2016-03-30 07:30:42", "opening_date": "1987-12-18", "display_title": "September", "link": {"url": "http://www.nytimes.com/movie/review?res=9B0DE2D91338F93BA25751C1A961948260", "suggested_link_text": "Read the New York Times Review of September", "type": "article"}, "mpaa_rating": "PG", "summary_short": "Endless whining on Vermont weekend. Woody Allen's first dud.", "multimedia": null}, {"headline": "LEONARD PART 6 (MOVIE)", "publication_date": "1987-12-18", "byline": "Caryn James", "critics_pick": 0, "date_updated": "2016-03-30 07:12:27", "opening_date": "1987-12-18", "display_title": "Leonard Part 6", "link": {"url": "http://www.nytimes.com/movie/review?res=9B0DEFD91F38F93BA25751C1A961948260", "suggested_link_text": "Read the New York Times Review of Leonard Part 6", "type": "article"}, "mpaa_rating": "PG", "summary_short": "Secret-agent adventure and perfectly awful. Bill's banana peel.", "multimedia": null}, {"headline": "IRONWEED (MOVIE)", "publication_date": "1987-12-18", "byline": "Janet Maslin", "critics_pick": 0, "date_updated": "2016-03-30 06:48:39", "opening_date": "1988-02-12", "display_title": "Ironweed", "link": {"url": "http://www.nytimes.com/movie/review?res=9B0DE5DB163BF93BA25751C1A961948260", "suggested_link_text": "Read the New York Times Review of Ironweed", "type": "article"}, "mpaa_rating": "R", "summary_short": "Albany derelicts, from Kennedy novel. Dreary.", "multimedia": null}, {"headline": "BATTERIES NOT INCLUDED (MOVIE)", "publication_date": "1987-12-18", "byline": "Janet Maslin", "critics_pick": 0, "date_updated": "2016-03-30 07:28:05", "opening_date": "1987-12-18", "display_title": "Batteries Not Included", "link": {"url": "http://www.nytimes.com/movie/review?res=9B0DE6DE153BF93BA25751C1A961948260", "suggested_link_text": "Read the New York Times Review of Batteries Not Included", "type": "article"}, "mpaa_rating": "PG", "summary_short": "Aliens help brownstone residents. Two veterans keep it going and going.", "multimedia": null}, {"headline": "DEAD, THE (MOVIE)", "publication_date": "1987-12-17", "byline": "Vincent Canby", "critics_pick": 1, "date_updated": "2016-03-30 07:13:14", "opening_date": "1987-12-18", "display_title": "The Dead", "link": {"url": "http://www.nytimes.com/movie/review?res=9B0DE7D81031F934A25751C1A961948260", "suggested_link_text": "Read the New York Times Review of The Dead", "type": "article"}, "mpaa_rating": "PG", "summary_short": "Dublin dinner party, 1904. Wonderfully evocative Joyce, via John Huston.", "multimedia": null}, {"headline": "BROADCAST NEWS (MOVIE)", "publication_date": "1987-12-16", "byline": "Vincent Canby", "critics_pick": 1, "date_updated": "2016-03-30 06:58:28", "opening_date": "1987-12-25", "display_title": "Broadcast News", "link": {"url": "http://www.nytimes.com/movie/review?res=9B0DE5DD113CF935A25751C1A961948260", "suggested_link_text": "Read the New York Times Review of Broadcast News", "type": "article"}, "mpaa_rating": "R", "summary_short": "Style vs. substance. Three smashing star performances.", "multimedia": null}, {"headline": "Spirit Moves, The: A History of Black Social Dance on Film (Movie)", "publication_date": "1987-12-16", "byline": "JENNIFER DUNNING", "critics_pick": 0, "date_updated": "2016-03-30 06:44:33", "opening_date": null, "display_title": "The Spirit Moves", "link": {"url": "http://www.nytimes.com/movie/review?res=9404E3DF153AF935A25751C1A961948260", "suggested_link_text": "Read the New York Times Review of The Spirit Moves", "type": "article"}, "mpaa_rating": "", "summary_short": "", "multimedia": null}, {"headline": "OVERBOARD (MOVIE)", "publication_date": "1987-12-16", "byline": "Janet Maslin", "critics_pick": 0, "date_updated": "2016-03-30 06:57:08", "opening_date": "1987-12-16", "display_title": "Overboard", "link": {"url": "http://www.nytimes.com/movie/review?res=9B0DE3DE133CF935A25751C1A961948260", "suggested_link_text": "Read the New York Times Review of Overboard", "type": "article"}, "mpaa_rating": "PG", "summary_short": "Amnesiac heiress in reduced circumstances. Sprightly caper.", "multimedia": null}, {"headline": "WILD PAIR, THE (MOVIE)", "publication_date": "1987-12-12", "byline": "Walter Goodman", "critics_pick": 0, "date_updated": "2016-03-30 06:48:37", "opening_date": null, "display_title": "The Wild Pair", "link": {"url": "http://www.nytimes.com/movie/review?res=9B0DE5DA143CF931A25751C1A961948260", "suggested_link_text": "Read the New York Times Review of The Wild Pair", "type": "article"}, "mpaa_rating": "R", "summary_short": "L.A. police on the trail of drugs and murder.", "multimedia": null}, {"headline": "WALL STREET (MOVIE)", "publication_date": "1987-12-11", "byline": "Vincent Canby", "critics_pick": 0, "date_updated": "2016-03-30 06:48:41", "opening_date": "1987-12-11", "display_title": "Wall Street", "link": {"url": "http://www.nytimes.com/movie/review?res=9B0DE6D61E38F932A25751C1A961948260", "suggested_link_text": "Read the New York Times Review of Wall Street", "type": "article"}, "mpaa_rating": "R", "summary_short": "Color of money, downtown. Brilliantly constructed, with feet of clay.", "multimedia": null}, {"headline": "THROW MOMMA FROM THE TRAIN (MOVIE)", "publication_date": "1987-12-11", "byline": "Janet Maslin", "critics_pick": 0, "date_updated": "2016-03-30 07:23:31", "opening_date": "1987-12-11", "display_title": "Throw Momma From the Train", "link": {"url": "http://www.nytimes.com/movie/review?res=9B0DE5D81139F932A25751C1A961948260", "suggested_link_text": "Read the New York Times Review of Throw Momma From the Train", "type": "article"}, "mpaa_rating": "PG-13", "summary_short": "Trading murders. Clever as it is original.", "multimedia": null}, {"headline": "EMPIRE OF THE SUN (MOVIE)", "publication_date": "1987-12-09", "byline": "Janet Maslin", "critics_pick": 1, "date_updated": "2016-03-30 07:11:57", "opening_date": "1987-12-25", "display_title": "Empire of the Sun", "link": {"url": "http://www.nytimes.com/movie/review?res=9B0DE1D9133DF93AA35751C1A961948260", "suggested_link_text": "Read the New York Times Review of Empire of the Sun", "type": "article"}, "mpaa_rating": "PG", "summary_short": "British boy swept into WWII Japanese camp, via Spielberg. Thrilling first half, rest O.K.", "multimedia": null}, {"headline": "HOME IS WHERE THE HART IS (MOVIE)", "publication_date": "1987-12-05", "byline": "CARYN JAMES", "critics_pick": 0, "date_updated": "2016-03-30 07:16:41", "opening_date": "1987-03-01", "display_title": "Square Dance", "link": {"url": "http://www.nytimes.com/movie/review?res=9B0DE0DE123AF936A35751C1A961948260", "suggested_link_text": "Read the New York Times Review of Square Dance", "type": "article"}, "mpaa_rating": "PG-13", "summary_short": "", "multimedia": null}, {"headline": "WALKER (MOVIE)", "publication_date": "1987-12-04", "byline": "Vincent Canby", "critics_pick": 0, "date_updated": "2016-03-30 07:12:44", "opening_date": "1987-12-04", "display_title": "Walker", "link": {"url": "http://www.nytimes.com/movie/review?res=9B0DE2DA1130F937A35751C1A961948260", "suggested_link_text": "Read the New York Times Review of Walker", "type": "article"}, "mpaa_rating": "R", "summary_short": "Witty political satire about William Walker, American who named himself Nicaragua's president in 1850's.", "multimedia": null}, {"headline": "TROUBLE WITH SPIES, THE (MOVIE)", "publication_date": "1987-12-04", "byline": "VINCENT CANBY", "critics_pick": 0, "date_updated": "2016-03-30 06:56:33", "opening_date": "1987-12-04", "display_title": "The Trouble With Spies", "link": {"url": "http://www.nytimes.com/movie/review?res=9B0DE7DB1030F937A35751C1A961948260", "suggested_link_text": "Read the New York Times Review of The Trouble With Spies", "type": "article"}, "mpaa_rating": "PG-13", "summary_short": "Bumbling British agent is bait for Soviets. Interesting idea, at first.", "multimedia": null}, {"headline": "STUDENT CONFIDENTIAL (MOVIE)", "publication_date": "1987-12-04", "byline": "Janet Maslin", "critics_pick": 0, "date_updated": "2016-03-30 07:28:49", "opening_date": "1987-06-01", "display_title": "Student Confidential", "link": {"url": "http://www.nytimes.com/movie/review?res=9B0DE0DE1439F937A35751C1A961948260", "suggested_link_text": "Read the New York Times Review of Student Confidential", "type": "article"}, "mpaa_rating": "R", "summary_short": "High-school counselor and four troubled students.", "multimedia": null}, {"headline": "REPENTANCE (MOVIE)", "publication_date": "1987-12-04", "byline": "JANET MASLIN", "critics_pick": 0, "date_updated": "2016-03-30 06:44:43", "opening_date": null, "display_title": "Monanieba", "link": {"url": "http://www.nytimes.com/movie/review?res=9B0DE5DB1730F937A35751C1A961948260", "suggested_link_text": "Read the New York Times Review of Monanieba", "type": "article"}, "mpaa_rating": "PG", "summary_short": "", "multimedia": null}, {"headline": "BLIND (MOTION PICTURE)", "publication_date": "1987-12-02", "byline": "Vincent Canby", "critics_pick": 0, "date_updated": "2016-03-30 06:52:03", "opening_date": null, "display_title": "Blind", "link": {"url": "http://www.nytimes.com/movie/review?res=9B0DE6DB1138F931A35751C1A961948260", "suggested_link_text": "Read the New York Times Review of Blind", "type": "article"}, "mpaa_rating": "", "summary_short": "", "multimedia": null}, {"headline": "HOUSEKEEPING (MOVIE)", "publication_date": "1987-11-25", "byline": "Vincent Canby", "critics_pick": 1, "date_updated": "2016-03-30 07:16:16", "opening_date": "1988-01-01", "display_title": "Housekeeping", "link": {"url": "http://www.nytimes.com/movie/review?res=9B0DE4D6103AF936A15752C1A961948260", "suggested_link_text": "Read the New York Times Review of Housekeeping", "type": "article"}, "mpaa_rating": "PG", "summary_short": "Small-town aunt and teenage sisters. Haunting comedy.", "multimedia": null}, {"headline": "THREE MEN AND A BABY (MOVIE)", "publication_date": "1987-11-25", "byline": "Janet Maslin", "critics_pick": 0, "date_updated": "2016-03-30 07:11:12", "opening_date": "1987-11-25", "display_title": "Three Men and A Baby", "link": {"url": "http://www.nytimes.com/movie/review?res=9B0DE3D9173DF936A15752C1A961948260", "suggested_link_text": "Read the New York Times Review of Three Men and A Baby", "type": "article"}, "mpaa_rating": "PG", "summary_short": "Swinging bachelors find abandoned infant. Charming comedy.", "multimedia": null}], "num_results": 20, "status": "OK", "copyright": "Copyright (c) 2017 The New York Times Company. All Rights Reserved.", "has_more": true}