{"results": [{"headline": "Countess from Hong Kong, A (Movie)", "publication_date": "1967-03-17", "byline": "BOSLEY CROWTHER", "critics_pick": 0, "date_updated": "2016-03-30 06:43:00", "opening_date": "1967-03-15", "display_title": "A Countess From Hong Kong", "link": {"url": "http://www.nytimes.com/movie/review?res=9401E0DA1539E53BBC4F52DFB566838C679EDE", "suggested_link_text": "Read the New York Times Review of A Countess From Hong Kong", "type": "article"}, "mpaa_rating": "G", "summary_short": "From hunger, even with the great Chaplin directing. Paging Charlie Chan.", "multimedia": null}, {"headline": "Mikado, The (Movie)", "publication_date": "1967-03-15", "byline": "DAN SULLIVAN", "critics_pick": 0, "date_updated": "2016-03-30 06:57:04", "opening_date": "1967-03-15", "display_title": "The Mikado", "link": {"url": "http://www.nytimes.com/movie/review?res=9B06E5DB1F3BE63ABC4D52DFB566838C679EDE", "suggested_link_text": "Read the New York Times Review of The Mikado", "type": "article"}, "mpaa_rating": "", "summary_short": "Skittish, misapplied movie technique stifles the magic of this D'Oyly Carte performace. The music survives.", "multimedia": null}, {"headline": "Ulysses (Movie)", "publication_date": "1967-03-14", "byline": "BOSLEY CROWTHER", "critics_pick": 0, "date_updated": "2016-03-30 06:42:25", "opening_date": null, "display_title": "Ulysses", "link": {"url": "http://www.nytimes.com/movie/review?res=9E07E5DD1F3BE63ABC4C52DFB566838C679EDE", "suggested_link_text": "Read the New York Times Review of Ulysses", "type": "article"}, "mpaa_rating": "", "summary_short": "", "multimedia": null}, {"headline": "How to Succeed in Business Without Really Trying (Movie)", "publication_date": "1967-03-10", "byline": "BOSLEY CROWTHER", "critics_pick": 0, "date_updated": "2016-03-30 07:13:29", "opening_date": "1967-03-09", "display_title": "How to Succeed in Business Without Really Trying", "link": {"url": "http://www.nytimes.com/movie/review?res=9B06E6D9113AEF33A25753C1A9659C946691D6CF", "suggested_link_text": "Read the New York Times Review of How to Succeed in Business Without Really Trying", "type": "article"}, "mpaa_rating": "", "summary_short": "The bright moments hold, from Broadway, ditto Loesser's score. But the seams show.", "multimedia": null}, {"headline": "Taming of the Shrew, The (Movie)", "publication_date": "1967-03-09", "byline": "BOSLEY CROWTHER", "critics_pick": 0, "date_updated": "2016-03-30 06:43:07", "opening_date": "1967-03-08", "display_title": "The Taming of the Shrew", "link": {"url": "http://www.nytimes.com/movie/review?res=9504E2D71E3BE63ABC4153DFB566838C679EDE", "suggested_link_text": "Read the New York Times Review of The Taming of the Shrew", "type": "article"}, "mpaa_rating": "", "summary_short": "Aggressively reluctant bride. Dazzlingly beautiful showcase for twin fire engines.", "multimedia": null}, {"headline": "PERSONA (MOVIE)", "publication_date": "1967-03-07", "byline": "Bosley Crowther", "critics_pick": 1, "date_updated": "2016-03-30 06:54:45", "opening_date": "1967-03-16", "display_title": "Persona", "link": {"url": "http://www.nytimes.com/movie/review?res=EE05E7DF173DE773BC4F53DFB566838C679EDE", "suggested_link_text": "Read the New York Times Review of Persona", "type": "article"}, "mpaa_rating": "Not Rated", "summary_short": "Severe-withdrawal patient and nurse. Typical Bergman probing, skilled and moving.", "multimedia": null}, {"headline": "Yo Yo (Movie)", "publication_date": "1967-03-01", "byline": "BOSLEY CROWTHER", "critics_pick": 0, "date_updated": "2016-03-30 06:48:52", "opening_date": null, "display_title": "Yoyo", "link": {"url": "http://www.nytimes.com/movie/review?res=9802E1DD1E3BE63ABC4953DFB566838C679EDE", "suggested_link_text": "Read the New York Times Review of Yoyo", "type": "article"}, "mpaa_rating": "Not Rated", "summary_short": "", "multimedia": null}, {"headline": "Dutchman (Movie)", "publication_date": "1967-02-28", "byline": "BOSLEY CROWTHER", "critics_pick": 0, "date_updated": "2016-03-30 06:48:03", "opening_date": null, "display_title": "The Dutchman", "link": {"url": "http://www.nytimes.com/movie/review?res=990DE2DE1E3CE53BBC4051DFB466838C679EDE", "suggested_link_text": "Read the New York Times Review of The Dutchman", "type": "article"}, "mpaa_rating": "", "summary_short": "LeRoi Jones's two-character play about white woman taunting black on subway. Ugly business, and more so, drawn in close.", "multimedia": null}, {"headline": "Corrupt Ones, The (Movie)", "publication_date": "1967-02-23", "byline": "BOSLEY CROWTHER", "critics_pick": 0, "date_updated": "2016-03-30 06:46:53", "opening_date": "1967-02-03", "display_title": "Il Sigillo di Pechino", "link": {"url": "http://www.nytimes.com/movie/review?res=9F06EED8103BE63ABC4B51DFB466838C679EDE", "suggested_link_text": "Read the New York Times Review of Il Sigillo di Pechino", "type": "article"}, "mpaa_rating": "", "summary_short": "Good action-adventure, grand Oriental locales but sags in last reel. Best in school.", "multimedia": null}, {"headline": "Deadlier Than the Male (Movie)", "publication_date": "1967-02-22", "byline": "BOSLEY CROWTHER", "critics_pick": 0, "date_updated": "2016-03-30 06:56:51", "opening_date": null, "display_title": "Deadlier Than the Male", "link": {"url": "http://www.nytimes.com/movie/review?res=9901EFD6113CE53BBC4A51DFB466838C679EDE", "suggested_link_text": "Read the New York Times Review of Deadlier Than the Male", "type": "article"}, "mpaa_rating": "", "summary_short": "A Bulldog Drummond crimer. New to us.", "multimedia": null}, {"headline": "My Sister, My Love (Movie)", "publication_date": "1967-02-20", "byline": "BOSLEY CROWTHER", "critics_pick": 0, "date_updated": "2016-03-30 07:09:57", "opening_date": null, "display_title": "Syskonbadd", "link": {"url": "http://www.nytimes.com/movie/review?res=9C06E6DB1F3CE43BBC4851DFB466838C679EDE", "suggested_link_text": "Read the New York Times Review of Syskonbadd", "type": "article"}, "mpaa_rating": "", "summary_short": "", "multimedia": null}, {"headline": "25th Hour, The (Movie)", "publication_date": "1967-02-17", "byline": "BOSLEY CROWTHER", "critics_pick": 0, "date_updated": "2016-03-30 07:16:06", "opening_date": null, "display_title": "La Vingt-cinquieme heure", "link": {"url": "http://www.nytimes.com/movie/review?res=9C00E6DC1F3CE43BBC4F52DFB466838C679EDE", "suggested_link_text": "Read the New York Times Review of La Vingt-cinquieme heure", "type": "article"}, "mpaa_rating": "", "summary_short": "Romanian peasant separated from family after World War II.", "multimedia": null}, {"headline": "New York Cinema Super Dragon (Movie)", "publication_date": "1967-02-16", "byline": "BOSLEY CROWTHER", "critics_pick": 0, "date_updated": "2016-03-30 07:19:13", "opening_date": "1967-02-15", "display_title": "New York Chiama Super Dragon", "link": {"url": "http://www.nytimes.com/movie/review?res=9905EFDE1F3CE43BBC4E52DFB466838C679EDE", "suggested_link_text": "Read the New York Times Review of New York Chiama Super Dragon", "type": "article"}, "mpaa_rating": "", "summary_short": "", "multimedia": null}, {"headline": "Journey to the Beginning of Time (Movie)", "publication_date": "1967-02-11", "byline": "HOWARD THOMPSON", "critics_pick": 0, "date_updated": "2016-03-30 07:26:23", "opening_date": "1966-00-00", "display_title": "Journey to the Beginning of Time", "link": {"url": "http://www.nytimes.com/movie/review?res=9504E3D6113CE43BBC4952DFB466838C679EDE", "suggested_link_text": "Read the New York Times Review of Journey to the Beginning of Time", "type": "article"}, "mpaa_rating": "", "summary_short": "", "multimedia": null}, {"headline": "Tobruk (Movie)", "publication_date": "1967-02-09", "byline": "HOWARD THOMPSON", "critics_pick": 0, "date_updated": "2016-03-30 07:11:57", "opening_date": "1967-02-07", "display_title": "Tobruk", "link": {"url": "http://www.nytimes.com/movie/review?res=9E0DE5D81439E53BBC4153DFB466838C679EDE", "suggested_link_text": "Read the New York Times Review of Tobruk", "type": "article"}, "mpaa_rating": "", "summary_short": "German Jews in British special forces unit. Graphic but unstartling war drama.", "multimedia": null}, {"headline": "Transport From Paradise (Movie)", "publication_date": "1967-02-08", "byline": "BOSLEY CROWTHER", "critics_pick": 0, "date_updated": "2016-03-30 07:11:21", "opening_date": null, "display_title": "Transport Z Raje", "link": {"url": "http://www.nytimes.com/movie/review?res=9F0DE5D91439E53BBC4053DFB466838C679EDE", "suggested_link_text": "Read the New York Times Review of Transport Z Raje", "type": "article"}, "mpaa_rating": "", "summary_short": "24 hours in the Nazi concentration camp at Theresienstadt.", "multimedia": null}, {"headline": "To be a Crook (Movie)", "publication_date": "1967-02-07", "byline": "BOSLEY CROWTHER", "critics_pick": 0, "date_updated": "2016-03-30 07:13:21", "opening_date": null, "display_title": "Une Fille Et Des Fusils", "link": {"url": "http://www.nytimes.com/movie/review?res=9C01E4DA1439E53BBC4F53DFB466838C679EDE", "suggested_link_text": "Read the New York Times Review of Une Fille Et Des Fusils", "type": "article"}, "mpaa_rating": "", "summary_short": "", "multimedia": null}, {"headline": "Night of the Generals, The (Movie)", "publication_date": "1967-02-03", "byline": "BOSLEY CROWTHER", "critics_pick": 0, "date_updated": "2016-03-30 06:42:09", "opening_date": "1967-02-24", "display_title": "The Night of the Generals", "link": {"url": "http://www.nytimes.com/movie/review?res=9A0DE1DC1439E53BBC4B53DFB466838C679EDE", "suggested_link_text": "Read the New York Times Review of The Night of the Generals", "type": "article"}, "mpaa_rating": "PG", "summary_short": "Stalking ex-Nazi officer. Stylishly intriguing.", "multimedia": null}, {"headline": "Fistful of Dollars, A (Movie)", "publication_date": "1967-02-02", "byline": "BOSLEY CROWTHER", "critics_pick": 0, "date_updated": "2016-03-30 06:55:41", "opening_date": "1967-01-18", "display_title": "A Fistful of Dollars", "link": {"url": "http://www.nytimes.com/movie/review?res=9B03E1DD1439E53BBC4A53DFB466838C679EDE", "suggested_link_text": "Read the New York Times Review of A Fistful of Dollars", "type": "article"}, "mpaa_rating": "", "summary_short": "Early, stolid Clint. Spaghetti sauce would have helped.", "multimedia": null}, {"headline": "Sweet Love, Bitter (Movie)", "publication_date": "1967-01-31", "byline": "BOSLEY CROWTHER", "critics_pick": 0, "date_updated": "2016-03-30 07:21:59", "opening_date": null, "display_title": "Sweet Love, Bitter", "link": {"url": "http://www.nytimes.com/movie/review?res=9800EFDC113CE53BBC4950DFB766838C679EDE", "suggested_link_text": "Read the New York Times Review of Sweet Love, Bitter", "type": "article"}, "mpaa_rating": "PG-13", "summary_short": "", "multimedia": null}], "num_results": 20, "status": "OK", "copyright": "Copyright (c) 2017 The New York Times Company. All Rights Reserved.", "has_more": true}