{"results": [{"headline": "DICE RULES (MOVIE)", "publication_date": "1991-05-18", "byline": "Janet Maslin", "critics_pick": 0, "date_updated": "2016-03-30 06:55:51", "opening_date": "1991-05-17", "display_title": "Dice Rules", "link": {"url": "http://www.nytimes.com/movie/review?res=9D0CE7DC1431F93BA25756C0A967958260", "suggested_link_text": "Read the New York Times Review of Dice Rules", "type": "article"}, "mpaa_rating": "NC-17", "summary_short": "One-man show.", "multimedia": null}, {"headline": "WHAT ABOUT BOB? (MOVIE)", "publication_date": "1991-05-17", "byline": "Janet Maslin", "critics_pick": 0, "date_updated": "2016-03-30 07:25:16", "opening_date": "1991-05-17", "display_title": "What About Bob?", "link": {"url": "http://www.nytimes.com/movie/review?res=9D0CE5DC1E3DF934A25756C0A967958260", "suggested_link_text": "Read the New York Times Review of What About Bob?", "type": "article"}, "mpaa_rating": "PG", "summary_short": "Patient plagues analyst. Really funny, till Murray closes in on family.", "multimedia": null}, {"headline": "TATIE DANIELLE (MOVIE)", "publication_date": "1991-05-17", "byline": "Janet Maslin", "critics_pick": 0, "date_updated": "2016-03-30 06:43:46", "opening_date": "1991-05-17", "display_title": "Tatie Danielle", "link": {"url": "http://www.nytimes.com/movie/review?res=9D0CEFD6143DF934A25756C0A967958260", "suggested_link_text": "Read the New York Times Review of Tatie Danielle", "type": "article"}, "mpaa_rating": "PG-13", "summary_short": "A malicious old lady delights in tyrannizing everyone around her. Directed by Etienne Chatiliez. Sly social satire.", "multimedia": null}, {"headline": "TERROR IN A TEXAS TOWN (MOVIE)", "publication_date": "1991-05-17", "byline": "STEPHEN HOLDEN", "critics_pick": 0, "date_updated": "2016-03-30 07:23:20", "opening_date": "1958-09-01", "display_title": "Terror in a Texas Town", "link": {"url": "http://www.nytimes.com/movie/review?res=9D0CEFDF1E3DF934A25756C0A967958260", "suggested_link_text": "Read the New York Times Review of Terror in a Texas Town", "type": "article"}, "mpaa_rating": "", "summary_short": "One asset: fine, final duel.", "multimedia": null}, {"headline": "Sweet Talker (Movie)", "publication_date": "1991-05-12", "byline": "JANET MASLIN", "critics_pick": 0, "date_updated": "2016-03-30 06:57:01", "opening_date": "1991-05-10", "display_title": "Sweet Talker", "link": {"url": "http://www.nytimes.com/movie/review?res=9905EFD7123AF931A25756C0A967958260", "suggested_link_text": "Read the New York Times Review of Sweet Talker", "type": "article"}, "mpaa_rating": "PG", "summary_short": "Con man and divorcee in small Australian coastal town. Overabundance of good spirits and squeaky-clean family fun.", "multimedia": null}, {"headline": "CHOPPER CHICKS IN ZOMBIETOWN (MOVIE)", "publication_date": "1991-05-10", "byline": "Stephen Holden", "critics_pick": 0, "date_updated": "2016-03-30 06:58:11", "opening_date": null, "display_title": "Chopper Chicks in Zombietown", "link": {"url": "http://www.nytimes.com/movie/review?res=9D0CE6DC1E3FF933A25756C0A967958260", "suggested_link_text": "Read the New York Times Review of Chopper Chicks in Zombietown", "type": "article"}, "mpaa_rating": "R", "summary_short": "What the world needs now. Help yourself.", "multimedia": null}, {"headline": "STRANGERS IN GOOD COMPANY (MOVIE)", "publication_date": "1991-05-10", "byline": "Janet Maslin", "critics_pick": 0, "date_updated": "2016-03-30 07:30:38", "opening_date": null, "display_title": "The Company of Strangers", "link": {"url": "http://www.nytimes.com/movie/review?res=9D0CEEDE153FF933A25756C0A967958260", "suggested_link_text": "Read the New York Times Review of The Company of Strangers", "type": "article"}, "mpaa_rating": "PG", "summary_short": "When their tour bus breaks down, a group of elderly women are marooned together for several days. With an empty vacation house at hand, the experience turns into a bracing respite for the group, among them a Mohawk Indian matriarch and a Philadelphia-born lesbian. Fish get caught in pantyhose nets but nothing too dramatic happens, not that it matters. As they share their lives and memories, the women gradually take shape while Cynthia Scott's film moves at its own slow, peaceful pace and arrives at a gratifying destination. \n", "multimedia": null}, {"headline": "TRUTH OR DARE (MOVIE)", "publication_date": "1991-05-10", "byline": "JANET MASLIN", "critics_pick": 0, "date_updated": "2016-03-30 07:10:34", "opening_date": "1991-05-24", "display_title": "Truth Or Dare", "link": {"url": "http://www.nytimes.com/movie/review?res=9D0CE2D9103CF933A25756C0A967958260", "suggested_link_text": "Read the New York Times Review of Truth Or Dare", "type": "article"}, "mpaa_rating": "R", "summary_short": "", "multimedia": null}, {"headline": "HERDSMEN OF THE SUN (MOVIE)", "publication_date": "1991-05-08", "byline": "JANET MASLIN", "critics_pick": 0, "date_updated": "2016-03-30 07:13:33", "opening_date": null, "display_title": "Herdsmen of the Sun", "link": {"url": "http://www.nytimes.com/movie/review?res=9D0CE1DD1E30F93BA35756C0A967958260", "suggested_link_text": "Read the New York Times Review of Herdsmen of the Sun", "type": "article"}, "mpaa_rating": "", "summary_short": "", "multimedia": null}, {"headline": "RICH GIRL (MOVIE)", "publication_date": "1991-05-04", "byline": "Janet Maslin", "critics_pick": 0, "date_updated": "2016-03-30 06:45:01", "opening_date": "1991-05-03", "display_title": "Rich Girl", "link": {"url": "http://www.nytimes.com/movie/review?res=9D0CE1D7133CF937A35756C0A967958260", "suggested_link_text": "Read the New York Times Review of Rich Girl", "type": "article"}, "mpaa_rating": "R", "summary_short": "Spoiled L.A. teen-ager falls for band singer.", "multimedia": null}, {"headline": "WATERDANCE, THE (MOVIE)", "publication_date": "1991-05-03", "byline": "Lawrence Van Gelder", "critics_pick": 1, "date_updated": "2016-03-30 06:46:59", "opening_date": "1992-05-13", "display_title": "The Waterdance", "link": {"url": "http://www.nytimes.com/movie/review?res=9D0CE5DC1E3BF930A35756C0A967958260", "suggested_link_text": "Read the New York Times Review of The Waterdance", "type": "article"}, "mpaa_rating": "R", "summary_short": "Heroism and humor as paraplegics learn to cope. Good, tightly constructed film with excellent cast.", "multimedia": null}, {"headline": "TRULY, MADLY, DEEPLY (MOVIE)", "publication_date": "1991-05-03", "byline": "VINCENT CANBY", "critics_pick": 0, "date_updated": "2016-03-30 07:21:26", "opening_date": "1991-05-24", "display_title": "Truly Madly Deeply", "link": {"url": "http://www.nytimes.com/movie/review?res=9D0CE1D7143AF930A35756C0A967958260", "suggested_link_text": "Read the New York Times Review of Truly Madly Deeply", "type": "article"}, "mpaa_rating": "PG", "summary_short": "A kind of British ``Ghost.'' Gooey, faddy, weepy.", "multimedia": null}, {"headline": "RAGE IN HARLEM, A (MOVIE)", "publication_date": "1991-05-03", "byline": "VINCENT CANBY", "critics_pick": 0, "date_updated": "2016-03-30 07:22:52", "opening_date": "1991-05-03", "display_title": "A Rage in Harlem", "link": {"url": "http://www.nytimes.com/movie/review?res=9D0CE5D7173BF930A35756C0A967958260", "suggested_link_text": "Read the New York Times Review of A Rage in Harlem", "type": "article"}, "mpaa_rating": "R", "summary_short": "Wise Mississippian causes complications. Colorful, pungent but uneven. Good cast.", "multimedia": null}, {"headline": "ONE GOOD COP (MOVIE)", "publication_date": "1991-05-03", "byline": "Janet Maslin", "critics_pick": 0, "date_updated": "2016-03-30 07:25:14", "opening_date": "1991-05-03", "display_title": "One Good Cop", "link": {"url": "http://www.nytimes.com/movie/review?res=9D0CE1DC153BF930A35756C0A967958260", "suggested_link_text": "Read the New York Times Review of One Good Cop", "type": "article"}, "mpaa_rating": "R", "summary_short": "Police officer and wife mind three orphans. Equal parts Dirty Harry and Mr. Mom. Doesn't click.", "multimedia": null}, {"headline": "China Cry (Movie)", "publication_date": "1991-05-03", "byline": "STEPHEN HOLDEN", "critics_pick": 0, "date_updated": "2016-03-30 06:58:53", "opening_date": "1990-11-02", "display_title": "China Cry", "link": {"url": "http://www.nytimes.com/movie/review?res=9C0DEFD7123AF930A35756C0A967958260", "suggested_link_text": "Read the New York Times Review of China Cry", "type": "article"}, "mpaa_rating": "PG-13", "summary_short": "", "multimedia": null}, {"headline": "EATING (MOVIE)", "publication_date": "1991-05-03", "byline": "Janet Maslin", "critics_pick": 0, "date_updated": "2016-03-30 07:23:25", "opening_date": "1990-11-30", "display_title": "Eating", "link": {"url": "http://www.nytimes.com/movie/review?res=9D0CE2DA143BF930A35756C0A967958260", "suggested_link_text": "Read the New York Times Review of Eating", "type": "article"}, "mpaa_rating": "R", "summary_short": "Yakking. Female gabfest at birthday party. Leisurely, insular, on its own island.", "multimedia": null}, {"headline": "Never Leave Nevada (Movie)", "publication_date": "1991-04-28", "byline": "STEPHEN HOLDEN", "critics_pick": 0, "date_updated": "2016-03-30 06:51:33", "opening_date": null, "display_title": "Never Leave Nevada", "link": {"url": "http://www.nytimes.com/movie/review?res=9507EED7123AF93BA15757C0A967958260", "suggested_link_text": "Read the New York Times Review of Never Leave Nevada", "type": "article"}, "mpaa_rating": "", "summary_short": "", "multimedia": null}, {"headline": "DROWNING BY NUMBERS (MOVIE)", "publication_date": "1991-04-26", "byline": "Janet Maslin", "critics_pick": 1, "date_updated": "2016-03-30 06:42:58", "opening_date": "1991-06-01", "display_title": "Drowning By Numbers", "link": {"url": "http://www.nytimes.com/movie/review?res=9D0CEEDD1730F935A15757C0A967958260", "suggested_link_text": "Read the New York Times Review of Drowning By Numbers", "type": "article"}, "mpaa_rating": "R", "summary_short": "English coroner and son play games with three deadly women.", "multimedia": null}, {"headline": "TOY SOLDIERS (MOVIE)", "publication_date": "1991-04-26", "byline": "Janet Maslin", "critics_pick": 0, "date_updated": "2016-03-30 07:12:28", "opening_date": "1991-04-26", "display_title": "Toy Soldiers", "link": {"url": "http://www.nytimes.com/movie/review?res=9D0CEFD91030F935A15757C0A967958260", "suggested_link_text": "Read the New York Times Review of Toy Soldiers", "type": "article"}, "mpaa_rating": "R", "summary_short": "Colombian terrorists hold prep school hostage. Crisp, suspenseful thriller, but the long arm of coincidence gets a real workout.", "multimedia": null}, {"headline": "OSCAR (MOVIE)", "publication_date": "1991-04-26", "byline": "Janet Maslin", "critics_pick": 0, "date_updated": "2016-03-30 06:41:26", "opening_date": "1991-04-26", "display_title": "Oscar", "link": {"url": "http://www.nytimes.com/movie/review?res=9D0CE2DD1030F935A15757C0A967958260", "suggested_link_text": "Read the New York Times Review of Oscar", "type": "article"}, "mpaa_rating": "PG", "summary_short": "Gangster goes respectable. Sly's genial sitcom debut. At least he's game, and the fun doesn't curdle.", "multimedia": null}], "num_results": 20, "status": "OK", "copyright": "Copyright (c) 2017 The New York Times Company. All Rights Reserved.", "has_more": true}